README.md
setup.py
clinical_sectionizer/__init__.py
clinical_sectionizer/_version.py
clinical_sectionizer/sectionizer.py
clinical_sectionizer/text_sectionizer.py
clinical_sectionizer/util.py
clinical_sectionizer.egg-info/PKG-INFO
clinical_sectionizer.egg-info/SOURCES.txt
clinical_sectionizer.egg-info/dependency_links.txt
clinical_sectionizer.egg-info/requires.txt
clinical_sectionizer.egg-info/top_level.txt
clinical_sectionizer/../resources/patrick_section_patterns.json
clinical_sectionizer/../resources/spacy_section_patterns.jsonl
clinical_sectionizer/../resources/text_section_patterns.jsonl