Metadata-Version: 2.1
Name: clinical-sectionizer
Version: 1.0.0.1
Summary: Document section detector using spaCy for clinical NLP
Home-page: UNKNOWN
Author: medSpaCy
Author-email: medspacy.dev@gmail.com
License: UNKNOWN
Platform: UNKNOWN
